parediffusers/__init__.py
parediffusers/defaults.py
parediffusers/pipeline.py
parediffusers/scheduler.py
parediffusers/unet.py
parediffusers/utils.py
parediffusers/vae.py
parediffusers/models/__init__.py
parediffusers/models/attension.py
parediffusers/models/embeddings.py
parediffusers/models/resnet.py
parediffusers/models/transformer.py
parediffusers/models/transformer_blocks.py
parediffusers/models/unet_2d_blocks.py
parediffusers/models/unet_2d_get_blocks.py
parediffusers/models/unet_2d_mid_blocks.py
parediffusers/models/vae_blocks.py
parediffusers-0.3.2.dist-info/METADATA
parediffusers-0.3.2.dist-info/WHEEL
parediffusers-0.3.2.dist-info/top_level.txt
parediffusers-0.3.2.dist-info/RECORD
