Metadata-Version: 2.1
Name: parediffusers
Version: 0.3.2
Summary: The library `pared` down the features of `diffusers` implemented the minimum function to generate images without using huggingface/diffusers to understand the inner workings of the library.
Home-page: https://github.com/masaishi/parediffusers
Author: Masamune Ishihara
Author-email: mwishiha@ucsc.edu
License: MIT License
Requires-Python: >=3.6
Requires-Dist: numpy
Requires-Dist: torch
Requires-Dist: torchvision
Requires-Dist: transformers
Requires-Dist: pillow
Requires-Dist: huggingface-hub
